Workbook

Sheet Transactions
A1: Transaction Register — June 2025
A2: # | B2: Description | C2: Amount (₹) | D2: Category | E2: Date | F2: Type
A3: 1 | B3: Monthly Salary | C3: 55000 | D3: Income | E3: 01-Jun-25 | F3: Credit
A4: 2 | B4: House Rent | C4: -12000 | D4: Housing | E4: 01-Jun-25 | F4: Debit
A5: 3 | B5: Grocery Shopping | C5: -4500 | D5: Food | E5: 03-Jun-25 | F5: Debit
A6: 4 | B6: Electricity Bill | C6: -1800 | D6: Utilities | E6: 05-Jun-25 | F6: Debit
A7: 5 | B7: Auto/Cab Rides | C7: -2200 | D7: Transport | E7: 06-Jun-25 | F7: Debit
A8: 6 | B8: Netflix & OTT | C8: -999 | D8: Entertainment | E8: 07-Jun-25 | F8: Debit
A9: 7 | B9: Doctor Consultation | C9: -800 | D9: Health | E9: 10-Jun-25 | F9: Debit
A10: 8 | B10: Online Course | C10: -1500 | D10: Education | E10: 12-Jun-25 | F10: Debit
A11: 9 | B11: Clothes Shopping | C11: -3500 | D11: Shopping | E11: 15-Jun-25 | F11: Debit
A12: 10 | B12: Mutual Fund SIP | C12: -5000 | D12: Savings | E12: 20-Jun-25 | F12: Debit
A13: 11 | B13: Miscellaneous | C13: -1200 | D13: Misc | E13: 25-Jun-25 | F13: Debit
A14: 12 | B14: Freelance Income | C14: 8000 | D14: Income | E14: 28-Jun-25 | F14: Credit
A15: NET BALANCE | C15: =SUM(C3:C14) -> 29501

Sheet Dashboard
A1: 💰 Personal Budget Tracker — Monthly Dashboard
B3: Total Income | C3: Total Expenses | D3: Net Savings | E3: Savings Rate
B4: =Transactions!C3+Transactions!C14 -> 63000 | C4: =ABS(SUM(Transactions!C4:C13)) -> 33499 | D4: =B4-C4 -> 29501 | E4: =IF(B4>0,D4/B4,0) -> 0.46826984
A6: Category | B6: Actual (₹) | C6: Budget (₹) | D6: % of Expenses | E6: Status
A7: Housing | B7: =ABS(Transactions!C4) -> 12000 | C7: 12000 | D7: =IF(C4>0,ABS(Transactions!C4)/C4,0) -> 0.35821965 | E7: =IF(B7>C7,"⚠ Over Budget","✅ OK") -> ✅ OK
A8: Food | B8: =ABS(Transactions!C5) -> 4500 | C8: 5000 | D8: =IF(C4>0,ABS(Transactions!C5)/C4,0) -> 0.13433237 | E8: =IF(B8>C8,"⚠ Over Budget","✅ OK") -> ✅ OK
A9: Transport | B9: =ABS(Transactions!C6) -> 1800 | C9: 2500 | D9: =IF(C4>0,ABS(Transactions!C6)/C4,0) -> 0.053732947 | E9: =IF(B9>C9,"⚠ Over Budget","✅ OK") -> ✅ OK
A10: Utilities | B10: =ABS(Transactions!C7) -> 2200 | C10: 2000 | D10: =IF(C4>0,ABS(Transactions!C7)/C4,0) -> 0.065673602 | E10: =IF(B10>C10,"⚠ Over Budget","✅ OK") -> ⚠ Over Budget
A11: Entertainment | B11: =ABS(Transactions!C8) -> 999 | C11: 1500 | D11: =IF(C4>0,ABS(Transactions!C8)/C4,0) -> 0.029821786 | E11: =IF(B11>C11,"⚠ Over Budget","✅ OK") -> ✅ OK
A12: Health | B12: =ABS(Transactions!C9) -> 800 | C12: 1000 | D12: =IF(C4>0,ABS(Transactions!C9)/C4,0) -> 0.02388131 | E12: =IF(B12>C12,"⚠ Over Budget","✅ OK") -> ✅ OK
A13: Education | B13: =ABS(Transactions!C10) -> 1500 | C13: 2000 | D13: =IF(C4>0,ABS(Transactions!C10)/C4,0) -> 0.044777456 | E13: =IF(B13>C13,"⚠ Over Budget","✅ OK") -> ✅ OK
A14: Shopping | B14: =ABS(Transactions!C11) -> 3500 | C14: 4000 | D14: =IF(C4>0,ABS(Transactions!C11)/C4,0) -> 0.10448073 | E14: =IF(B14>C14,"⚠ Over Budget","✅ OK") -> ✅ OK
A15: Savings | B15: =ABS(Transactions!C12) -> 5000 | C15: 5000 | D15: =IF(C4>0,ABS(Transactions!C12)/C4,0) -> 0.14925819 | E15: =IF(B15>C15,"⚠ Over Budget","✅ OK") -> ✅ OK
A16: Misc | B16: =ABS(Transactions!C13) -> 1200 | C16: 1500 | D16: =IF(C4>0,ABS(Transactions!C13)/C4,0) -> 0.035821965 | E16: =IF(B16>C16,"⚠ Over Budget","✅ OK") -> ✅ OK
A18: Average Expense per Category: | B18: =AVERAGE(B7:B16) -> 3349.9

Sheet Budget Plan
A1: Monthly Budget Plan vs Actual
A2: # | B2: Category | C2: Planned (₹) | D2: Actual (₹) | E2: Variance (₹) | F2: Status
A3: 1 | B3: Housing | C3: 12000 | D3: =ABS(Transactions!C4) -> 12000 | E3: =C3-D3 -> 0 | F3: =IF(E3>=0,"✅ Under Budget","⚠ Over Budget") -> ✅ Under Budget
A4: 2 | B4: Food | C4: 5000 | D4: =ABS(Transactions!C5) -> 4500 | E4: =C4-D4 -> 500 | F4: =IF(E4>=0,"✅ Under Budget","⚠ Over Budget") -> ✅ Under Budget
A5: 3 | B5: Transport | C5: 2500 | D5: =ABS(Transactions!C6) -> 1800 | E5: =C5-D5 -> 700 | F5: =IF(E5>=0,"✅ Under Budget","⚠ Over Budget") -> ✅ Under Budget
A6: 4 | B6: Utilities | C6: 2000 | D6: =ABS(Transactions!C7) -> 2200 | E6: =C6-D6 -> -200 | F6: =IF(E6>=0,"✅ Under Budget","⚠ Over Budget") -> ⚠ Over Budget
A7: 5 | B7: Entertainment | C7: 1500 | D7: =ABS(Transactions!C8) -> 999 | E7: =C7-D7 -> 501 | F7: =IF(E7>=0,"✅ Under Budget","⚠ Over Budget") -> ✅ Under Budget
A8: 6 | B8: Health | C8: 1000 | D8: =ABS(Transactions!C9) -> 800 | E8: =C8-D8 -> 200 | F8: =IF(E8>=0,"✅ Under Budget","⚠ Over Budget") -> ✅ Under Budget
A9: 7 | B9: Education | C9: 2000 | D9: =ABS(Transactions!C10) -> 1500 | E9: =C9-D9 -> 500 | F9: =IF(E9>=0,"✅ Under Budget","⚠ Over Budget") -> ✅ Under Budget
A10: 8 | B10: Shopping | C10: 4000 | D10: =ABS(Transactions!C11) -> 3500 | E10: =C10-D10 -> 500 | F10: =IF(E10>=0,"✅ Under Budget","⚠ Over Budget") -> ✅ Under Budget
A11: 9 | B11: Savings | C11: 5000 | D11: =ABS(Transactions!C12) -> 5000 | E11: =C11-D11 -> 0 | F11: =IF(E11>=0,"✅ Under Budget","⚠ Over Budget") -> ✅ Under Budget
A12: 10 | B12: Misc | C12: 1500 | D12: =ABS(Transactions!C13) -> 1200 | E12: =C12-D12 -> 300 | F12: =IF(E12>=0,"✅ Under Budget","⚠ Over Budget") -> ✅ Under Budget
A13: TOTAL | C13: =SUM(C3:C12) -> 36500 | D13: =SUM(D3:D12) -> 33499 | E13: =SUM(E3:E12) -> 3001

Sheet Charts
A1: Visual Spending Analysis
A2: Category | B2: Amount
A3: Housing | B3: =ABS(Transactions!C4) -> 12000
A4: Food | B4: =ABS(Transactions!C5) -> 4500
A5: Transport | B5: =ABS(Transactions!C6) -> 1800
A6: Utilities | B6: =ABS(Transactions!C7) -> 2200
A7: Entertainment | B7: =ABS(Transactions!C8) -> 999
A8: Health | B8: =ABS(Transactions!C9) -> 800
A9: Education | B9: =ABS(Transactions!C10) -> 1500
A10: Shopping | B10: =ABS(Transactions!C11) -> 3500
A11: Savings | B11: =ABS(Transactions!C12) -> 5000
A12: Misc | B12: =ABS(Transactions!C13) -> 1200
